opencatwebjson/__init__.py
opencatwebjson/classes.py
opencatwebjson/elements.py
opencatwebjson/literals.py
opencatwebjson-0.0.3.dist-info/METADATA
opencatwebjson-0.0.3.dist-info/WHEEL
opencatwebjson-0.0.3.dist-info/licenses/LICENSE
opencatwebjson-0.0.3.dist-info/RECORD
