Metadata-Version: 2.4
Name: opencatwebjson
Version: 0.0.3
Summary: Python Library for handling CatWeb's JSON Formats
License: GPLv3
License-File: LICENSE
Keywords: parser,json,catweb,roblox
Requires-Python: >=3.10
Classifier: Programming Language :: Python :: 3
Classifier: License :: OSI Approved :: GNU General Public License v3 (GPLv3)
Classifier: Operating System :: OS Independent
Requires-Dist: orjson (>=3.11.3,<4.0.0)
